FalconSignedSessions/__init__.py
FalconSignedSessions/tests.py
FalconSignedSessions-0.0.3.dist-info/LICENSE
FalconSignedSessions-0.0.3.dist-info/METADATA
FalconSignedSessions-0.0.3.dist-info/WHEEL
FalconSignedSessions-0.0.3.dist-info/top_level.txt
FalconSignedSessions-0.0.3.dist-info/RECORD
