Metadata-Version: 2.1
Name: FalconSignedSessions
Version: 0.0.3
Summary: Signed & trusted sessions for falcon.
Home-page: https://github.com/WardPearce/falcon-signed-cookies
Author: WardPearce
Author-email: wardpearce@pm.me
License: AGPL v3
Platform: UNKNOWN
License-File: LICENSE
Requires-Dist: itsdangerous
Requires-Dist: falcon
